Workbook

Sheet Summary
A1: Quarter Report
A2: Source | B2: https://lookerstudio.google.com/reporting/ce9802de-e3e3-4b1a-b730-21d2352a9d55/page/p_2rqnedbhbd
A3: Quarter | B3: Q4 2025
A4: Date Range | B4: 2025-10-01 to 2025-12-31
A5: Generated | B5: 2026-03-24 15:04:12
A7: Metric | B7: Quarter Total / Avg | C7: Formula | E7: Highlights | F7: Value
A8: Impressions | B8: =SUM(Monthly!B2:B4) | C8: =SUM(Monthly!B2:B4) | E8: Top campaign by spend | F8: [ADa] - PMax: All products - Search
A9: Clicks | B9: =SUM(Monthly!C2:C4) | C9: =SUM(Monthly!C2:C4) | E9: Top device by spend | F9: mobile devices with full browsers
A10: CTR | B10: =SUM(Monthly!C2:C4)/SUM(Monthly!B2:B4) | C10: =SUM(Monthly!C2:C4)/SUM(Monthly!B2:B4) | E10: Top geo by spend | F10: Australia
A11: Avg CPC | B11: =SUM(Monthly!F2:F4)/SUM(Monthly!C2:C4) | C11: =SUM(Monthly!F2:F4)/SUM(Monthly!C2:C4) | E11: Highest monthly ROAS | F11: 2025-12-01
A12: Cost | B12: =SUM(Monthly!F2:F4) | C12: =SUM(Monthly!F2:F4) | E12: Highest monthly conversions | F12: 2025-11-01
A13: Revenue | B13: =SUM(Monthly!G2:G4) | C13: =SUM(Monthly!G2:G4)
A14: Profit | B14: =B13-B12 | C14: =B13-B12
A15: Conversions | B15: =SUM(Monthly!I2:I4) | C15: =SUM(Monthly!I2:I4)
A16: CPA | B16: =SUM(Monthly!F2:F4)/SUM(Monthly!I2:I4) | C16: =SUM(Monthly!F2:F4)/SUM(Monthly!I2:I4)
A17: Conv. Rate | B17: =SUM(Monthly!I2:I4)/SUM(Monthly!C2:C4) | C17: =SUM(Monthly!I2:I4)/SUM(Monthly!C2:C4)
A18: ROAS | B18: =SUM(Monthly!G2:G4)/SUM(Monthly!F2:F4) | C18: =SUM(Monthly!G2:G4)/SUM(Monthly!F2:F4)
A19: Value / Conv. | B19: =SUM(Monthly!G2:G4)/SUM(Monthly!I2:I4) | C19: =SUM(Monthly!G2:G4)/SUM(Monthly!I2:I4)

Sheet Monthly
A1: Month | B1: Impressions | C1: Clicks | D1: CTR | E1: Avg CPC | F1: Cost | G1: Revenue | H1: Profit | I1: Conversions | J1: CPA | K1: Conv. Rate | L1: ROAS | M1: Value / Conv.
A2: 2025-10-01 | B2: 268930 | C2: 4380 | D2: 0.016286766 | E2: 1.069648 | F2: 4685.0585 | G2: 32999.33 | H2: 28314.272 | I2: 243 | J2: 19.280076 | K2: 0.053103147 | L2: 7.0435259 | M2: 135.79971
A3: 2025-11-01 | B3: 385047 | C3: 6786 | D3: 0.017623823 | E3: 1.1097283 | F3: 7530.6161 | G3: 74406.792 | H3: 66876.176 | I3: 543 | J3: 13.868538 | K3: 0.075228595 | L3: 9.8805717 | M3: 137.02908
A4: 2025-12-01 | B4: 436603 | C4: 4999 | D4: 0.011449761 | E4: 1.2879421 | F4: 6438.4228 | G4: 2404590.5 | H4: 2398152.1 | I4: 245 | J4: 26.279277 | K4: 0.043493698 | L4: 373.47508 | M4: 9814.655

Sheet Campaign Breakdown
A1: Exact Q4 2025 campaign breakdown from the same public Looker Studio source.
A3: Campaign state | B3: Base Campaign Name | C3: Impressions | D3: Clicks | E3: CTR | F3: CPC | G3: Cost | H3: Revenue | I3: Profit | J3: Conversions | K3: CPA | L3: Conv. Rate | M3: ROAS
A4: active | B4: [ADa] - PMax: All products - Search | C4: 726865 | D4: 8176 | E4: 0.011248306 | F4: 1.1663691 | G4: 9536.2337 | H4: 61656.251 | I4: 52120.017 | J4: 398 | K4: 23.960386 | L4: 0.046236059 | M4: 6.4654718
A5: active | B5: [ADa] - PMax: different signals - bestsellers | C5: 210699 | D5: 3234 | E5: 0.01534891 | F5: 1.5405584 | G5: 4982.1659 | H5: 27966.917 | I5: 22984.751 | J5: 169 | K5: 29.480271 | L5: 0.045332618 | M5: 5.6134054
A6: active | B6: Megaphone - Brand Terms | C6: 10235 | D6: 3090 | E6: 0.30190523 | F6: 0.7327653 | G6: 2264.2448 | H6: 2412511.3 | I6: 2410247.1 | J6: 395 | K6: 5.7322653 | L6: 0.12783172 | M6: 1065.4817
A7: paused | B7: [ADa] - PMax: All products - Baby care | C7: 142781 | D7: 1665 | E7: 0.011661215 | F7: 1.1239958 | G7: 1871.453 | H7: 9862.0903 | I7: 7990.6373 | J7: 69 | K7: 27.122507 | L7: 0.034482759 | M7: 5.2697504
A8: paused | B8: AUS - Shopping Campaign - April 2024 | C8: 0 | D8: 0 | E8: 0 | F8: 0 | G8: 0 | H8: 0 | I8: 0 | J8: 0 | K8: 0 | L8: 0 | M8: 0
A9: paused | B9: learning bucket 2024_6_5 17_43 | C9: 0 | D9: 0 | E9: 0 | F9: 0 | G9: 0 | H9: 0 | I9: 0 | J9: 0 | K9: 0 | L9: 0 | M9: 0
A10: paused | B10: Megaphone - Search - Baby Books | C10: 0 | D10: 0 | E10: 0 | F10: 0 | G10: 0 | H10: 0 | I10: 0 | J10: 0 | K10: 0 | L10: 0 | M10: 0
A11: paused | B11: Megaphone - Search - Best Children's Books | C11: 0 | D11: 0 | E11: 0 | F11: 0 | G11: 0 | H11: 0 | I11: 0 | J11: 0 | K11: 0 | L11: 0 | M11: 0
A12: paused | B12: Megaphone - Search - Busy Book | C12: 0 | D12: 0 | E12: 0 | F12: 0 | G12: 0 | H12: 0 | I12: 0 | J12: 0 | K12: 0 | L12: 0 | M12: 0
A13: paused | B13: Megaphone - Search - DSA | C13: 0 | D13: 0 | E13: 0 | F13: 0 | G13: 0 | H13: 0 | I13: 0 | J13: 0 | K13: 0 | L13: 0 | M13: 0
A14: paused | B14: Megaphone - Search - Picture Books | C14: 0 | D14: 0 | E14: 0 | F14: 0 | G14: 0 | H14: 0 | I14: 0 | J14: 0 | K14: 0 | L14: 0 | M14: 0
A15: paused | B15: Megaphone - Search - Quiet Book | C15: 0 | D15: 0 | E15: 0 | F15: 0 | G15: 0 | H15: 0 | I15: 0 | J15: 0 | K15: 0 | L15: 0 | M15: 0
... A66: paused | B66: Megaphone - Retargeting - Responsive Display | C66: 0 | D66: 0 | E66: 0 | F66: 0 | G66: 0 | H66: 0 | I66: 0 | J66: 0 | K66: 0 | L66: 0 | M66: 0

Sheet Device Breakdown
A1: Exact Q4 2025 device breakdown from the same public Looker Studio source.
A3: Device | B3: Impressions | C3: Clicks | D3: CTR | E3: CPC | F3: Cost | G3: Revenue | H3: Profit | I3: Conversions | J3: CPA | K3: Conv. Rate | L3: ROAS
A4: mobile devices with full browsers | B4: 850718 | C4: 14014 | D4: 0.016473144 | E4: 1.0834739 | F4: 15183.803 | G4: 2484571.9 | H4: 2469388.1 | I4: 842 | J4: 18.03302 | K4: 0.056441882 | L4: 163.63305
A5: computers | B5: 135768 | C5: 1926 | D5: 0.014185964 | E5: 1.7064408 | F5: 3286.6051 | G5: 24941.941 | H5: 21655.335 | I5: 176 | J5: 18.673892 | K5: 0.085478388 | L5: 7.5889679
A6: tablets with full browsers | B6: 103968 | C6: 220 | D6: 0.0021160357 | E6: 0.8256559 | F6: 181.6443 | G6: 2338.81 | H6: 2157.1657 | I6: 12 | J6: 15.137025 | K6: 0.027777778 | L6: 12.875769
A7: TV screens | B7: 37 | C7: 0 | D7: 0 | E7: 0 | F7: 1.311852 | G7: 0 | H7: -1.311852 | I7: 0 | J7: 0 | K7: 0 | L7: 0
A8: unknown | B8: 89 | C8: 5 | D8: 0.056179775 | E8: 0.1467138 | F8: 0.733569 | G8: 143.9 | H8: 143.16643 | I8: 1 | J8: 0.733569 | K8: 0.2 | L8: 196.16423

Sheet Geo Breakdown
A1: Exact Q4 2025 geo breakdown from the same public Looker Studio source.
A3: Country/Territory | B3: Impressions | C3: Clicks | D3: CTR | E3: CPC | F3: Cost | G3: Revenue | H3: Profit | I3: Conversions | J3: CPA | K3: Conv. Rate | L3: ROAS
A4: Australia | B4: 1087291 | C4: 15119 | D4: 0.013905201 | E4: 1.1423961 | F4: 17271.887 | G4: 131195.08 | H4: 113923.19 | I4: 914 | J4: 18.897032 | K4: 0.055796349 | L4: 7.5958739
A5: United States | B5: 2043 | C5: 667 | D5: 0.32648067 | E5: 1.5145124 | F5: 1010.1798 | G5: 2376875.7 | H5: 2375865.5 | I5: 87 | J5: 11.611262 | K5: 0.13043478 | L5: 2352.9234
A6: Canada | B6: 500 | C6: 131 | D6: 0.262 | E6: 1.6525107 | F6: 216.4789 | G6: 896.24 | H6: 679.7611 | I6: 6 | J6: 36.079816 | K6: 0.045801527 | L6: 4.1400802
A7: New Zealand | B7: 575 | C7: 204 | D7: 0.35478261 | E7: 0.70645392 | F7: 144.1166 | G7: 2375.22 | H7: 2231.1034 | I7: 19 | J7: 7.5850842 | K7: 0.093137255 | L7: 16.481238
A8: Singapore | B8: 171 | C8: 44 | D8: 0.25730994 | E8: 0.25988357 | F8: 11.434877 | G8: 404.4 | H8: 392.96512 | I8: 2 | J8: 5.7174385 | K8: 0.045454545 | L8: 35.365488

Sheet Weekly Detail
A1: Supplementary weekly rows overlapping Q4 2025. Quarter totals on Summary use exact month-level data, not these overlapping weeks.
A3: Week Start | B3: Week End | C3: Impressions | D3: Clicks | E3: CTR | F3: CPC | G3: Cost | H3: Revenue | I3: Profit | J3: Conversions | K3: CPA | L3: Conv. Rate | M3: ROAS
A4: 2025-12-29 | B4: 2026-01-04 | C4: 61862 | D4: 664 | E4: 0.010733568 | F4: 1.2482516 | G4: 828.83906 | H4: 3720.1154 | I4: 2891.2763 | J4: 30 | K4: 27.627969 | L4: 0.026455026 | M4: 4.4883447
A5: 2025-12-22 | B5: 2025-12-28 | C5: 77337 | D5: 795 | E5: 0.010279685 | F5: 1.2082674 | G5: 960.57261 | H5: 2218.41 | I5: 1257.8374 | J5: 17 | K5: 56.504271 | L5: 0.017471737 | M5: 2.3094662
A6: 2025-12-15 | B6: 2025-12-21 | C6: 98719 | D6: 998 | E6: 0.010109503 | F6: 1.3207217 | G6: 1318.0802 | H6: 5726.8456 | I6: 4408.7653 | J6: 40 | K6: 32.952006 | L6: 0.038314176 | M6: 4.3448383
A7: 2025-12-08 | B7: 2025-12-14 | C7: 117821 | D7: 1363 | E7: 0.011568396 | F7: 1.3290778 | G7: 1811.5331 | H7: 10546.194 | I7: 8734.6614 | J7: 68 | K7: 26.640192 | L7: 0.046575342 | M7: 5.8216958
A8: 2025-12-01 | B8: 2025-12-07 | C8: 112995 | D8: 1534 | E8: 0.013575822 | F8: 1.2757339 | G8: 1956.9759 | H8: 2385059.3 | I8: 2383102.3 | J8: 111 | K8: 17.630413 | L8: 0.070075758 | M8: 1218.7474
A9: 2025-11-24 | B9: 2025-11-30 | C9: 106754 | D9: 1723 | E9: 0.01613991 | F9: 1.1575288 | G9: 1994.4221 | H9: 22755.698 | I9: 20761.275 | J9: 161 | K9: 12.387715 | L9: 0.089944134 | M9: 11.40967
A10: 2025-11-17 | B10: 2025-11-23 | C10: 98269 | D10: 1753 | E10: 0.017838789 | F10: 1.1864083 | G10: 2079.7738 | H10: 16704.596 | I10: 14624.822 | J10: 126 | K10: 16.506141 | L10: 0.066072365 | M10: 8.0319292
A11: 2025-11-10 | B11: 2025-11-16 | C11: 85787 | D11: 1539 | E11: 0.017939781 | F11: 1.0619433 | G11: 1634.3307 | H11: 17847.997 | I11: 16213.666 | J11: 134 | K11: 12.196498 | L11: 0.077726218 | M11: 10.920677
A12: 2025-11-03 | B12: 2025-11-09 | C12: 75511 | D12: 1399 | E12: 0.018527102 | F12: 1.0208917 | G12: 1428.2275 | H12: 12656.33 | I12: 11228.103 | J12: 91 | K12: 15.694808 | L12: 0.064129669 | M12: 8.8615648
A13: 2025-10-27 | B13: 2025-11-02 | C13: 67568 | D13: 1160 | E13: 0.01716789 | F13: 1.1100532 | G13: 1287.6617 | H13: 10082.523 | I13: 8794.8618 | J13: 71 | K13: 18.13608 | L13: 0.060271647 | M13: 7.830103
A14: 2025-10-20 | B14: 2025-10-26 | C14: 63972 | D14: 1018 | E14: 0.015913212 | F14: 1.0952949 | G14: 1115.0103 | H14: 9198.223 | I14: 8083.2127 | J14: 67 | K14: 16.641944 | L14: 0.06344697 | M14: 8.2494515
A15: 2025-10-13 | B15: 2025-10-19 | C15: 61597 | D15: 1036 | E15: 0.016819001 | F15: 0.95985967 | G15: 994.41462 | H15: 7535.8789 | I15: 6541.4643 | J15: 57 | K15: 17.44587 | L15: 0.051959891 | M15: 7.5782061
... A17: 2025-09-29 | B17: 2025-10-05 | C17: 53806 | D17: 764 | E17: 0.01419916 | F17: 1.0951339 | G17: 836.68229 | H17: 5411.2642 | I17: 4574.5819 | J17: 40 | K17: 20.917057 | L17: 0.048019208 | M17: 6.4675257

Sheet Notes
A1: Source URL | B1: https://lookerstudio.google.com/reporting/ce9802de-e3e3-4b1a-b730-21d2352a9d55/page/p_2rqnedbhbd
A2: Quarter | B2: Previous completed quarter relative to 2026-03-24: Q4 2025
A3: Date range | B3: 2025-10-01 to 2025-12-31
A4: Method | B4: Pulled public Looker Studio data via the report?s own batchedData endpoint and combined it into one workbook.
A5: Important note | B5: Weekly sheet contains overlapping calendar weeks; Summary and Monthly sheets are the exact quarter views.
A6: Cost normalization | B6: The custom month-level query returned cost in micros, normalized to currency units before writing the workbook.
